fatum/__init__.py
fatum/py.typed
fatum/client/__init__.py
fatum/client/base.py
fatum/client/errors.py
fatum/client/types.py
fatum/experiment/__init__.py
fatum/experiment/exceptions.py
fatum/experiment/experiment.py
fatum/experiment/protocols.py
fatum/experiment/tracker.py
fatum/experiment/types.py
fatum/profiler/__init__.py
fatum/profiler/timer.py
fatum/pydanticonf/__init__.py
fatum/pydanticonf/settings.py
fatum/reproducibility/__init__.py
fatum/reproducibility/git.py
fatum/reproducibility/system.py
fatum/structify/__init__.py
fatum/structify/enums.py
fatum/structify/factory.py
fatum/structify/hooks.py
fatum/structify/models.py
fatum/structify/types.py
fatum/structify/adapters/__init__.py
fatum/structify/adapters/anthropic.py
fatum/structify/adapters/azure_openai.py
fatum/structify/adapters/base.py
fatum/structify/adapters/gemini.py
fatum/structify/adapters/openai.py
fatum-27.0.0.dist-info/METADATA
fatum-27.0.0.dist-info/WHEEL
fatum-27.0.0.dist-info/RECORD
